uroboros/__init__.py
uroboros/command.py
uroboros/constants.py
uroboros/errors.py
uroboros/option.py
uroboros/utils.py
uroboros-0.2.4.dist-info/LICENSE
uroboros-0.2.4.dist-info/METADATA
uroboros-0.2.4.dist-info/WHEEL
uroboros-0.2.4.dist-info/top_level.txt
uroboros-0.2.4.dist-info/RECORD
