Metadata-Version: 2.1
Name: uroboros
Version: 0.2.4
Summary: Simple framework for building scalable CLI tool
Home-page: https://github.com/pddg/uroboros
Author: Shoma Kokuryo
Author-email: pudding@mail.poyo.info
License: UNKNOWN
Platform: UNKNOWN
Classifier: Development Status :: 3 - Alpha
Classifier: Intended Audience :: Developers
Classifier: License :: OSI Approved :: Apache Software License
Classifier: Programming Language :: Python
Classifier: Programming Language :: Python :: 3.5
Classifier: Programming Language :: Python :: 3.6
Classifier: Programming Language :: Python :: 3.7
Classifier: Programming Language :: Python :: 3.8
Requires-Python: >=3.5
